moth/__init__.py
moth/projects.py
gin_moth-0.1.0.dist-info/METADATA
gin_moth-0.1.0.dist-info/WHEEL
gin_moth-0.1.0.dist-info/top_level.txt
gin_moth-0.1.0.dist-info/RECORD
