Metadata-Version: 2.1
Name: gin-moth
Version: 0.1.0
Summary: Memory-efficient On-the-fly Tiling of Histological images
Author: Thomas Kauer
Project-URL: Homepage, https://github.com/Neuropathology-Giessen/MOTH
Classifier: Programming Language :: Python :: 3
Classifier: Operating System :: OS Independent
Classifier: License :: OSI Approved :: GNU General Public License v3 (GPLv3)
Requires-Python: >=3.9
Requires-Dist: paquo <0.8,>=0.7
Requires-Dist: rasterio <1.4,>=1.3
Requires-Dist: tiffslide <2.2,>=2.1
Provides-Extra: docs
Requires-Dist: Sphinx <7.4,>=7.3 ; extra == 'docs'
Requires-Dist: sphinx-rtd-theme <2.1,>=2.0 ; extra == 'docs'
Requires-Dist: sphinx-autodoc-typehints <2.3,>=2.2 ; extra == 'docs'
